pydantic_builder/__init__.py
pydantic_builder/example.py
pydantic_builder/main.py
pydantic_builder/py.typed
pydantic_builder-0.1.0.dist-info/licenses/LICENSE
pydantic_builder-0.1.0.dist-info/METADATA
pydantic_builder-0.1.0.dist-info/WHEEL
pydantic_builder-0.1.0.dist-info/top_level.txt
pydantic_builder-0.1.0.dist-info/RECORD
