Metadata-Version: 2.4
Name: pydantic_builder
Version: 0.1.0
Summary: A micro framework implementing a convenient type parameterized builder pattern for pydantic models
Requires-Python: >=3.10
License-File: LICENSE
Requires-Dist: pydantic>=2.0.0
Requires-Dist: typing-extensions>=4.0.0; python_version < "3.11"
Dynamic: license-file
